policyengine_api_full_client/__init__.py
policyengine_api_full_client/api/__init__.py
policyengine_api_full_client/api/default/__init__.py
policyengine_api_full_client/api/default/alive_ping_alive_get.py
policyengine_api_full_client/api/default/create_houshold_household_post.py
policyengine_api_full_client/api/default/create_user_user_post.py
policyengine_api_full_client/api/default/delete_household_household_id_delete.py
policyengine_api_full_client/api/default/delete_user_user_id_delete.py
policyengine_api_full_client/api/default/get_household_household_id_get.py
policyengine_api_full_client/api/default/get_user_user_id_get.py
policyengine_api_full_client/api/default/ping_ping_post.py
policyengine_api_full_client/api/default/started_ping_started_get.py
policyengine_api_full_client/client.py
policyengine_api_full_client/errors.py
policyengine_api_full_client/models/__init__.py
policyengine_api_full_client/models/health_status.py
policyengine_api_full_client/models/household.py
policyengine_api_full_client/models/household_create.py
policyengine_api_full_client/models/http_validation_error.py
policyengine_api_full_client/models/ping_request.py
policyengine_api_full_client/models/ping_response.py
policyengine_api_full_client/models/probe_status.py
policyengine_api_full_client/models/system_status.py
policyengine_api_full_client/models/user_create.py
policyengine_api_full_client/models/user_private.py
policyengine_api_full_client/models/user_public.py
policyengine_api_full_client/models/validation_error.py
policyengine_api_full_client/py.typed
policyengine_api_full_client/types.py
policyengine_api_full_client-0.20260120.83.dist-info/METADATA
policyengine_api_full_client-0.20260120.83.dist-info/WHEEL
policyengine_api_full_client-0.20260120.83.dist-info/RECORD
